xiyou_sdk/__init__.py
xiyou_sdk/auth.py
xiyou_sdk/client.py
xiyou_sdk-1.1.0.dist-info/LICENSE
xiyou_sdk-1.1.0.dist-info/METADATA
xiyou_sdk-1.1.0.dist-info/WHEEL
xiyou_sdk-1.1.0.dist-info/top_level.txt
xiyou_sdk-1.1.0.dist-info/RECORD
