Metadata-Version: 2.1
Name: xiyou_sdk
Version: 1.1.0
Summary: Xiyou OpenAPI Python SDK - 提供完整的API功能（支持同步和异步调用）
Home-page: https://github.com/xiyou/xiyou-python-sdk
Author: Xiyou SDK Team
Author-email: Xiyou SDK Team <support@xiyou.com>
License: MIT
Project-URL: Homepage, https://github.com/xiyou/xiyou-python-sdk
Project-URL: Bug Reports, https://github.com/xiyou/xiyou-python-sdk/issues
Project-URL: Source, https://github.com/xiyou/xiyou-python-sdk
Project-URL: Documentation, https://docs.xiyou.com
Keywords: xiyou,api,sdk,auth,signature,hmac,authentication,amazon,asin,async
Classifier: Development Status :: 5 - Production/Stable
Classifier: Intended Audience :: Developers
Classifier: License :: OSI Approved :: MIT License
Classifier: Operating System :: OS Independent
Classifier: Programming Language :: Python :: 3
Classifier: Programming Language :: Python :: 3.7
Classifier: Programming Language :: Python :: 3.8
Classifier: Programming Language :: Python :: 3.9
Classifier: Programming Language :: Python :: 3.10
Classifier: Programming Language :: Python :: 3.11
Classifier: Topic :: Software Development :: Libraries :: Python Modules
Classifier: Topic :: Internet :: WWW/HTTP :: Dynamic Content
Classifier: Topic :: Security :: Cryptography
Requires-Python: >=3.7
License-File: LICENSE
Requires-Dist: requests>=2.25.0
Requires-Dist: aiohttp>=3.8.0
